README.rst
setup.py
GetCaptchaText/__init__.py
GetCaptchaText/captcha.py
GetCaptchaText/setup.py
GetCaptchaText.egg-info/PKG-INFO
GetCaptchaText.egg-info/SOURCES.txt
GetCaptchaText.egg-info/dependency_links.txt
GetCaptchaText.egg-info/requires.txt
GetCaptchaText.egg-info/top_level.txt